spectastic/__init__.py
spectastic/errors.py
spectastic/operation.py
spectastic/request.py
spectastic/schema.py
spectastic/validators.py
spectastic/contrib/__init__.py
spectastic/contrib/flask_utils.py
spectastic-0.3.2.dist-info/METADATA
spectastic-0.3.2.dist-info/RECORD
spectastic-0.3.2.dist-info/WHEEL
spectastic-0.3.2.dist-info/top_level.txt
