Metadata-Version: 2.1
Name: spectastic
Version: 0.3.2
Summary: Request and response validation compatible with swagger.
Home-page: https://github.com/planetlabs/spectastic
Author: Jacob Straszynski
Author-email: jacob.straszynski@planet.com
License: Apache 2
Keywords: spectastic
Platform: UNKNOWN
Classifier: Development Status :: 2 - Pre-Alpha
Classifier: Intended Audience :: Developers
Classifier: Natural Language :: English
Classifier: Programming Language :: Python :: 2
Classifier: Programming Language :: Python :: 2.7
Classifier: Programming Language :: Python :: 3
Classifier: Programming Language :: Python :: 3.3
Classifier: Programming Language :: Python :: 3.4
Requires-Dist: jsonschema
Requires-Dist: werkzeug
Requires-Dist: strict-rfc3339
Requires-Dist: six
Requires-Dist: future
